eipy/__init__.py
eipy/additional_ensembles.py
eipy/datasets.py
eipy/ei.py
eipy/interpretation.py
eipy/metrics.py
eipy/utils.py
ensemble_integration-0.1.6.dist-info/COPYING
ensemble_integration-0.1.6.dist-info/METADATA
ensemble_integration-0.1.6.dist-info/WHEEL
ensemble_integration-0.1.6.dist-info/RECORD
