Metadata-Version: 2.1
Name: ensemble-integration
Version: 0.1.6
Summary: Ensemble Integration: a customizable pipeline for generating multi-modal, heterogeneous ensembles
License: GNU General Public License version 3
Author: Jamie Bennett
Requires-Python: >=3.8
Classifier: License :: OSI Approved :: GNU General Public License v3 (GPLv3)
Classifier: License :: Other/Proprietary License
Classifier: Operating System :: MacOS
Classifier: Operating System :: Microsoft :: Windows
Classifier: Operating System :: OS Independent
Classifier: Operating System :: POSIX :: Linux
Classifier: Programming Language :: Python :: 3
Classifier: Programming Language :: Python :: 3.8
Classifier: Programming Language :: Python :: 3.9
Classifier: Programming Language :: Python :: 3.10
Classifier: Programming Language :: Python :: 3.11
Classifier: Programming Language :: Python :: 3.12
Requires-Dist: dill (>=0.3.7,<0.4.0)
Requires-Dist: imbalanced-learn (>=0.11)
Requires-Dist: joblib (>=1.3)
Requires-Dist: numpy (>=1.24)
Requires-Dist: pandas (>=1.4)
Requires-Dist: pandoc (>=2.3,<3.0)
Requires-Dist: scikit-learn (>=1.2,<1.3)
Requires-Dist: scipy (>=1.0,<1.12) ; python_version >= "3.8" and python_version < "3.13"
Requires-Dist: tqdm (>=4.66.2,<5.0.0)
Requires-Dist: wget (>=3.2,<4.0)
Requires-Dist: xgboost (>=1.7)
Project-URL: Documentation, https://eipy.readthedocs.io/en/latest/
Project-URL: Homepage, https://github.com/GauravPandeyLab/eipy
